descript_mlx/__init__.py
descript_mlx/model/__init__.py
descript_mlx/model/base.py
descript_mlx/model/dac.py
descript_mlx/nn/__init__.py
descript_mlx/nn/layers.py
descript_mlx/nn/quantize.py
descript_mlx-0.0.2.dist-info/LICENSE
descript_mlx-0.0.2.dist-info/METADATA
descript_mlx-0.0.2.dist-info/WHEEL
descript_mlx-0.0.2.dist-info/top_level.txt
descript_mlx-0.0.2.dist-info/RECORD
