Metadata-Version: 2.1
Name: descript-mlx
Version: 0.0.2
Summary: Descript Audio Codec - MLX
Author-email: Lucas Newman <lucasnewman@me.com>
License: MIT
Project-URL: Homepage, https://github.com/lucasnewman/descript-mlx
Keywords: artificial intelligence,asr,audio-generation,deep learning,transformers,text-to-speech
Classifier: Development Status :: 4 - Beta
Classifier: Intended Audience :: Developers
Classifier: Topic :: Scientific/Engineering :: Artificial Intelligence
Classifier: License :: OSI Approved :: MIT License
Classifier: Programming Language :: Python :: 3.9
Requires-Python: >=3.9
License-File: LICENSE
Requires-Dist: einops
Requires-Dist: huggingface-hub
Requires-Dist: mlx >=0.18.1
Requires-Dist: numpy
Requires-Dist: setuptools
Requires-Dist: soundfile
